Metadata-Version: 1.1
Name: CoreTracker
Version: 1.4.8
Summary: CoreTracker, A codon reassignment tracker
Home-page: https://github.com/UdeM-LBIT/CoreTracker
Author: Emmanuel Noutahi
Author-email: fmr.noutahi@umontreal.ca
License: GPL
Download-URL: https://github.com/UdeM-LBIT/CoreTracker/archive/1.4.8.tar.gz
Keywords: bioinformatics codon reassignment tracker
Platform: UNKNOWN
Classifier: Development Status :: 4 - Beta
Classifier: Environment :: Console
Classifier: Natural Language :: English
Classifier: Intended Audience :: Developers
Classifier: Intended Audience :: Science/Research
Classifier: License :: OSI Approved :: GNU General Public License (GPL)
Classifier: Operating System :: POSIX
Classifier: Programming Language :: Python :: 2.7
